Metadata-Version: 2.1
Name: sphinx-litprog
Version: 0.1.1
Summary: A literate programming extension for Sphinx
Home-page: https://github.com/torfsen/sphinx-litprog
Author: Florian Brucker
Author-email: mail@florianbrucker.de
License: MIT
Keywords: sphinx,literate programming
Platform: UNKNOWN
Classifier: Development Status :: 4 - Beta
Classifier: Framework :: Sphinx :: Extension
Classifier: Intended Audience :: Developers
Classifier: License :: OSI Approved :: MIT License
Classifier: Programming Language :: Python :: 3 :: Only
Classifier: Topic :: Documentation :: Sphinx
Classifier: Topic :: Software Development :: Documentation
